{
    "characters": [
        {
            "cId": 1,
            "name": "丁",
            "strokes": [ 
                1, 9
            ]
        },
        {
            "cId": 2,
            "name": "山",
            "strokes": [ 
                2, 3, 3
            ]
        },
        {
            "cId": 3,
            "name": "板",
            "strokes": [
                22, 26, 3, 4, 3, 3, 10, 6
              ]
        },
        {
            "cId": 4,
            "name": "绊",
            "strokes":[
                13, 13, 7, 4, 3,  1, 1, 2
            ]
        }
    ]
}